flask_tenable/__init__.py
Flask_Tenable-1.4.13.post1.dist-info/METADATA
Flask_Tenable-1.4.13.post1.dist-info/WHEEL
Flask_Tenable-1.4.13.post1.dist-info/top_level.txt
Flask_Tenable-1.4.13.post1.dist-info/RECORD
