Metadata-Version: 2.1
Name: Flask-Tenable
Version: 1.4.13.post1
Summary: Flask-Tenable is a thin wrapper for pyTenable that enables the easy integration of pyTenable into flask applications.
Home-page: https://github.com/felix-zenk/flask-tenable
Author: Felix Zenk
Author-email: felix.zenk@web.de
License: MIT
Project-URL: Source, https://github.com/felix-zenk/flask-tenable
Project-URL: Documentation, https://pytenable.readthedocs.io/en/stable/
Requires-Python: >=3.6, <4
